{
  "id": "1030P",
  "name": "1030 (Previsão) - Terminal Ibirité / Novo Horizonte",
  "labels": {
    "prev": "Previsão - Ônibus que está voltando do bairro Vila Ideal, o hórario de saída é apenas uma estimativa"
  },
  "workingDays": [
    "05:40:prev",
    "07:20:prev",
    "08:10:prev",
    "09:00:prev",
    "10:35:prev",
    "11:50:prev",
    "13:50:prev",
    "15:50:prev",
    "17:10:prev",
    "19:00:prev",
    "19:40:prev",
    "20:20:prev",
    "22:00:prev"
  ],
  "saturdays": [
    "06:30:prev",
    "08:20:prev",
    "10:15:prev",
    "11:35:prev",
    "12:55:prev",
    "15:55:prev",
    "17:25:prev",
    "18:55:prev",
    "20:55:prev"
  ],
  "sundays": [
    "07:50:prev",
    "09:10:prev",
    "11:10:prev",
    "12:40:prev",
    "14:50:prev",
    "16:35:prev",
    "18:10:prev",
    "19:50:prev"
  ]
}
