{
  "id": "1013P",
  "name": "1013 - (Previsão) Terminal Ibirité / Jardim das Rosas / Palmeiras",
  "labels": {
    "prev": "Previsão - Ônibus que está voltando do bairro Recanto das Árvores, o hórario de saída é apenas uma estimativa"
  },
  "workingDays": [
    "06:00:prev",
    "07:20:prev",
    "08:10:prev",
    "09:30:prev",
    "11:50:prev",
    "12:40:prev",
    "14:00:prev",
    "15:10:prev",
    "16:10:prev",
    "17:35:prev",
    "18:20:prev",
    "19:40:prev",
    "21:40:prev"
  ],
  "saturdays": [
    "06:15:prev",
    "07:55:prev",
    "09:35:prev",
    "11:15:prev",
    "13:15:prev",
    "14:55:prev",
    "16:35:prev",
    "18:15:prev",
    "20:10:prev"
  ],
  "sundays": [
    "06:15:prev",
    "08:00:prev",
    "09:45:prev",
    "11:30:prev",
    "13:30:prev",
    "15:30:prev",
    "17:30:prev",
    "19:30:prev"
  ]
}
