{
  "id": "1015P",
  "name": "1015 - (Previsão) Terminal Ibirité / Palmeiras - Fazendinha",
  "labels": {
    "prev": "(Previsão) - Terminal Ibirité / Palmeiras - Fazendinha",
    "pi": "Partida do bairro"
  },
  "workingDays": [
    "05:10:pi",
    "05:55",
    "06:25",
    "06:55",
    "07:55",
    "08:55",
    "10:15",
    "11:45",
    "13:15",
    "14:45",
    "16:15",
    "17:15",
    "18:15",
    "19:20",
    "20:45"
  ],
  "saturdays": [
    "05:30:pi",
    "06:15",
    "07:35",
    "08:45",
    "09:55",
    "10:55",
    "12:55",
    "14:40",
    "16:25",
    "18:10",
    "20:15"
  ],
  "sundays": [
    "06:10",
    "08:45",
    "10:45",
    "12:45",
    "14:45",
    "16:45",
    "18:45",
    "20:45"
  ]
}
