{
  "id": "1030P",
  "name": "1030 - (Previsão) Terminal Ibirité / Novo Horizonte",
  "labels": {
    "prev": "(Previsão) - Terminal Ibirité / Novo Horizonte"
  },
  "workingDays": [
    "05:30:prev",
    "06:20:prev",
    "07:20:prev",
    "08:10:prev",
    "09:10:prev",
    "11:05:prev",
    "12:30:prev",
    "13:30:prev",
    "14:30:prev",
    "15:30:prev",
    "16:30:prev",
    "17:30:prev",
    "18:30:prev",
    "19:40:prev",
    "21:00:prev"
  ],
  "saturdays": [
    "06:30:prev",
    "08:00:prev",
    "09:30:prev",
    "11:00:prev",
    "12:30:prev",
    "14:00:prev",
    "15:30:prev",
    "17:00:prev",
    "18:30:prev",
    "20:30:prev"
  ],
  "sundays": [
    "06:00:prev",
    "07:30:prev",
    "09:00:prev",
    "10:30:prev",
    "12:00:prev",
    "13:30:prev",
    "15:00:prev",
    "16:30:prev",
    "18:00:prev",
    "19:30:prev",
    "21:00:prev"
  ]
}
